slrkit/__init__.py
slrkit/acronyms.py
slrkit/exploreres.py
slrkit/filter_paper.py
slrkit/ga_param.toml
slrkit/gen_terms.py
slrkit/heatmap.py
slrkit/import_biblio.py
slrkit/join_lda_info.py
slrkit/journal_lister.py
slrkit/lda.py
slrkit/lda_ga.py
slrkit/merge_labels.py
slrkit/postprocess.py
slrkit/preprocess.py
slrkit/ris_visualizer.py
slrkit/schwartz_hearst.py
slrkit/slrkit.py
slrkit/stopword_extractor.py
slrkit/topic_report.py
slrkit/utils.py
slrkit/version.py
slrkit/default_stopwords/custom_stopwords_en.txt
slrkit/default_stopwords/nltk_stopwords_en.txt
slrkit/report_templates/placeholder.png
slrkit/report_templates/report_template.md
slrkit/report_templates/report_template.tex
slrkit-1.4.0.dist-info/licenses/LICENSE
slrkit-1.4.0.dist-info/METADATA
slrkit-1.4.0.dist-info/WHEEL
slrkit-1.4.0.dist-info/entry_points.txt
slrkit-1.4.0.dist-info/top_level.txt
slrkit-1.4.0.dist-info/RECORD
