Metadata-Version: 2.4
Name: slrkit
Version: 1.4.0
Summary: Tools to automatize systematic literature reviews
Home-page: https://github.com/robolab-pavia/slrkit
Author: Tullio Facchinetti
Author-email: tullio.facchinetti@unipv.it
License: GPL-3.0-or-later
Classifier: Programming Language :: Python :: 3
Classifier: Operating System :: OS Independent
Classifier: License :: OSI Approved :: GNU General Public License v3 (GPLv3)
Requires-Python: >=3.6
License-File: LICENSE
Requires-Dist: pyparsing==2.2.1
Requires-Dist: gensim
Requires-Dist: matplotlib
Requires-Dist: nltk
Requires-Dist: numpy
Requires-Dist: pandas
Requires-Dist: rispy
Requires-Dist: regex
Requires-Dist: psutil
Requires-Dist: treetaggerwrapper
Requires-Dist: fawoc
Requires-Dist: tabulate
Requires-Dist: Jinja2
Requires-Dist: tomlkit
Requires-Dist: deap
Requires-Dist: GitPython
Requires-Dist: slrkit-utils
Dynamic: license-file
